formularity_dag/__init__.py
formularity_dag/decorators.py
formularity_dag/graph.py
formularity_dag/nodes.py
formularity_dag/placeholders.py
formularity_dag/utils.py
formularity_dag-0.1.0.dist-info/METADATA
formularity_dag-0.1.0.dist-info/WHEEL
formularity_dag-0.1.0.dist-info/RECORD
