Metadata-Version: 2.4
Name: formularity-dag
Version: 0.1.0
Summary: A declarative Python library for building computation DAGs
Project-URL: Homepage, https://github.com/zzk/formularity
Project-URL: Repository, https://github.com/zzk/formularity
License-Expression: MIT
Keywords: computation,dag,dataflow,formula,graph,reactive
Classifier: Development Status :: 4 - Beta
Classifier: Intended Audience :: Developers
Classifier: License :: OSI Approved :: MIT License
Classifier: Programming Language :: Python :: 3
Classifier: Programming Language :: Python :: 3.10
Classifier: Programming Language :: Python :: 3.11
Classifier: Programming Language :: Python :: 3.12
Classifier: Programming Language :: Python :: 3.13
Classifier: Topic :: Software Development :: Libraries :: Python Modules
Requires-Python: >=3.10
Provides-Extra: json
Requires-Dist: dataclasses-json>=0.6.0; extra == 'json'
